{"coord": {"lon": 85.1376, "lat": 25.5941}, "list": [{"main": {"aqi": 3}, "components": {"co": 687.6, "no": 0, "no2": 12.51, "o3": 62.23, "so2": 12.04, "pm2_5": 40.5, "pm10": 46.85, "nh3": 10.77}, "dt": 1719000000}, {"main": {"aqi": 3}, "components": {"co": 720.98, "no": 0, "no2": 13.02, "o3": 58.65, "so2": 12.04, "pm2_5": 48.53, "pm10": 53.29, "nh3": 7.16}, "dt": 1719003600}, {"main": {"aqi": 4}, "components": {"co": 727.65, "no": 0, "no2": 13.54, "o3": 55.07, "so2": 12.16, "pm2_5": 50, "pm10": 54.2, "nh3": 5.07}, "dt": 1719007200}, {"main": {"aqi": 3}, "components": {"co": 694.27, "no": 0, "no2": 12.51, "o3": 57.94, "so2": 10.85, "pm2_5": 47.67, "pm10": 51.69, "nh3": 4.5}, "dt": 1719010800}, {"main": {"aqi": 3}, "components": {"co": 694.27, "no": 0, "no2": 11.48, "o3": 61.51, "so2": 10.13, "pm2_5": 48.48, "pm10": 52.65, "nh3": 4.62}, "dt": 1719014400}, {"main": {"aqi": 4}, "components": {"co": 734.33, "no": 0.17, "no2": 12, "o3": 55.79, "so2": 10.85, "pm2_5": 50.99, "pm10": 56.36, "nh3": 5.45}, "dt": 1719018000}, {"main": {"aqi": 4}, "components": {"co": 807.76, "no": 1.05, "no2": 13.19, "o3": 52.93, "so2": 13.23, "pm2_5": 54.59, "pm10": 62.22, "nh3": 7.16}, "dt": 1719021600}, {"main": {"aqi": 4}, "components": {"co": 854.49, "no": 1.56, "no2": 13.71, "o3": 70.1, "so2": 15.5, "pm2_5": 60.52, "pm10": 69.66, "nh3": 8.74}, "dt": 1719025200}, {"main": {"aqi": 5}, "components": {"co": 854.49, "no": 0.91, "no2": 10.8, "o3": 101.57, "so2": 15.74, "pm2_5": 76.49, "pm10": 84.71, "nh3": 5.89}, "dt": 1719028800}, {"main": {"aqi": 5}, "components": {"co": 881.2, "no": 0.48, "no2": 10.11, "o3": 124.45, "so2": 17.64, "pm2_5": 94.61, "pm10": 102.26, "nh3": 3.23}, "dt": 1719032400}, {"main": {"aqi": 5}, "components": {"co": 881.2, "no": 0.18, "no2": 10.97, "o3": 131.61, "so2": 19.07, "pm2_5": 104.26, "pm10": 111.64, "nh3": 2.01}, "dt": 1719036000}, {"main": {"aqi": 5}, "components": {"co": 814.44, "no": 0.16, "no2": 10.54, "o3": 133.04, "so2": 17.64, "pm2_5": 97.29, "pm10": 103.43, "nh3": 1.74}, "dt": 1719039600}, {"main": {"aqi": 5}, "components": {"co": 727.65, "no": 0.31, "no2": 8.31, "o3": 150.2, "so2": 14.9, "pm2_5": 92.65, "pm10": 97.71, "nh3": 1.55}, "dt": 1719043200}, {"main": {"aqi": 5}, "components": {"co": 700.95, "no": 0.32, "no2": 6.77, "o3": 174.52, "so2": 13.83, "pm2_5": 98.55, "pm10": 103.35, "nh3": 1.23}, "dt": 1719046800}, {"main": {"aqi": 5}, "components": {"co": 700.95, "no": 0.26, "no2": 6.68, "o3": 191.69, "so2": 13.35, "pm2_5": 103.22, "pm10": 108.13, "nh3": 1.09}, "dt": 1719050400}, {"main": {"aqi": 5}, "components": {"co": 707.63, "no": 0.17, "no2": 7.37, "o3": 191.69, "so2": 13.11, "pm2_5": 98.75, "pm10": 103.62, "nh3": 1.11}, "dt": 1719054000}, {"main": {"aqi": 5}, "components": {"co": 700.95, "no": 0.07, "no2": 8.23, "o3": 181.67, "so2": 12.76, "pm2_5": 86.85, "pm10": 91.39, "nh3": 1.3}, "dt": 1719057600}, {"main": {"aqi": 5}, "components": {"co": 727.65, "no": 0.01, "no2": 11.14, "o3": 165.94, "so2": 14.9, "pm2_5": 79.98, "pm10": 85.43, "nh3": 3.39}, "dt": 1719061200}, {"main": {"aqi": 5}, "components": {"co": 774.38, "no": 0, "no2": 13.02, "o3": 147.34, "so2": 17.4, "pm2_5": 78.74, "pm10": 86.78, "nh3": 6.84}, "dt": 1719064800}, {"main": {"aqi": 5}, "components": {"co": 801.09, "no": 0, "no2": 13.88, "o3": 131.61, "so2": 18.84, "pm2_5": 80.77, "pm10": 91.43, "nh3": 9.88}, "dt": 1719068400}, {"main": {"aqi": 5}, "components": {"co": 827.79, "no": 0, "no2": 14.39, "o3": 118.73, "so2": 20.27, "pm2_5": 87.67, "pm10": 99.98, "nh3": 12.03}, "dt": 1719072000}, {"main": {"aqi": 5}, "components": {"co": 847.82, "no": 0, "no2": 13.71, "o3": 114.44, "so2": 20.5, "pm2_5": 93.97, "pm10": 106.4, "nh3": 12.54}, "dt": 1719075600}, {"main": {"aqi": 5}, "components": {"co": 801.09, "no": 0, "no2": 11.65, "o3": 118.73, "so2": 16.69, "pm2_5": 85.73, "pm10": 96.34, "nh3": 12.03}, "dt": 1719079200}, {"main": {"aqi": 4}, "components": {"co": 694.27, "no": 0, "no2": 9.17, "o3": 125.89, "so2": 14.31, "pm2_5": 73.56, "pm10": 81.28, "nh3": 10.01}, "dt": 1719082800}]}