{"coord": {"lon": 85.1376, "lat": 25.5941}, "list": [{"main": {"aqi": 4}, "components": {"co": 574.11, "no": 0, "no2": 11.31, "o3": 101.57, "so2": 20.27, "pm2_5": 58.63, "pm10": 69.17, "nh3": 11.15}, "dt": 1716494400}, {"main": {"aqi": 4}, "components": {"co": 594.14, "no": 0, "no2": 11.48, "o3": 92.98, "so2": 20.74, "pm2_5": 61.97, "pm10": 73.01, "nh3": 10.89}, "dt": 1716498000}, {"main": {"aqi": 4}, "components": {"co": 614.17, "no": 0, "no2": 12.17, "o3": 82.25, "so2": 19.79, "pm2_5": 64.45, "pm10": 75.82, "nh3": 10.26}, "dt": 1716501600}, {"main": {"aqi": 4}, "components": {"co": 634.19, "no": 0, "no2": 13.02, "o3": 72.24, "so2": 18.36, "pm2_5": 66.04, "pm10": 77.62, "nh3": 9.88}, "dt": 1716505200}, {"main": {"aqi": 4}, "components": {"co": 667.57, "no": 0, "no2": 14.22, "o3": 63.66, "so2": 17.4, "pm2_5": 67.75, "pm10": 79.89, "nh3": 9.88}, "dt": 1716508800}, {"main": {"aqi": 4}, "components": {"co": 707.63, "no": 0.25, "no2": 15.94, "o3": 55.79, "so2": 17.88, "pm2_5": 69.65, "pm10": 83.17, "nh3": 10.77}, "dt": 1716512400}, {"main": {"aqi": 4}, "components": {"co": 774.38, "no": 1.41, "no2": 16.96, "o3": 60.8, "so2": 20.27, "pm2_5": 74.47, "pm10": 90.58, "nh3": 12.79}, "dt": 1716516000}, {"main": {"aqi": 5}, "components": {"co": 781.06, "no": 1.79, "no2": 15.59, "o3": 91.55, "so2": 23.13, "pm2_5": 81.77, "pm10": 99.12, "nh3": 13.43}, "dt": 1716519600}, {"main": {"aqi": 4}, "components": {"co": 520.71, "no": 0.56, "no2": 5.83, "o3": 137.33, "so2": 17.17, "pm2_5": 62.82, "pm10": 72.84, "nh3": 5.76}, "dt": 1716523200}, {"main": {"aqi": 4}, "components": {"co": 447.27, "no": 0.29, "no2": 3.3, "o3": 158.79, "so2": 14.07, "pm2_5": 60.26, "pm10": 68.18, "nh3": 3.36}, "dt": 1716526800}, {"main": {"aqi": 4}, "components": {"co": 427.25, "no": 0.25, "no2": 2.87, "o3": 163.08, "so2": 12.28, "pm2_5": 59.25, "pm10": 66.61, "nh3": 2.91}, "dt": 1716530400}, {"main": {"aqi": 4}, "components": {"co": 417.23, "no": 0.25, "no2": 2.83, "o3": 164.51, "so2": 11.56, "pm2_5": 58.91, "pm10": 66.01, "nh3": 2.79}, "dt": 1716534000}, {"main": {"aqi": 4}, "components": {"co": 413.89, "no": 0.25, "no2": 3, "o3": 167.37, "so2": 11.44, "pm2_5": 59.64, "pm10": 66.75, "nh3": 2.82}, "dt": 1716537600}, {"main": {"aqi": 4}, "components": {"co": 410.56, "no": 0.26, "no2": 3.34, "o3": 170.23, "so2": 11.92, "pm2_5": 60.32, "pm10": 67.5, "nh3": 2.79}, "dt": 1716541200}, {"main": {"aqi": 4}, "components": {"co": 447.27, "no": 0.38, "no2": 6, "o3": 175.95, "so2": 16.21, "pm2_5": 65.05, "pm10": 73.28, "nh3": 4.02}, "dt": 1716544800}, {"main": {"aqi": 4}, "components": {"co": 500.68, "no": 0.38, "no2": 9.42, "o3": 177.38, "so2": 20.27, "pm2_5": 70.64, "pm10": 80.3, "nh3": 5.76}, "dt": 1716548400}, {"main": {"aqi": 4}, "components": {"co": 540.73, "no": 0.2, "no2": 12.51, "o3": 167.37, "so2": 22.41, "pm2_5": 72.54, "pm10": 83.27, "nh3": 7.22}, "dt": 1716552000}, {"main": {"aqi": 4}, "components": {"co": 574.11, "no": 0.02, "no2": 13.37, "o3": 155.93, "so2": 23.37, "pm2_5": 72.15, "pm10": 84.1, "nh3": 8.87}, "dt": 1716555600}, {"main": {"aqi": 4}, "components": {"co": 620.84, "no": 0, "no2": 13.71, "o3": 137.33, "so2": 23.84, "pm2_5": 71.24, "pm10": 85.12, "nh3": 11.4}, "dt": 1716559200}, {"main": {"aqi": 4}, "components": {"co": 674.25, "no": 0, "no2": 15.08, "o3": 118.73, "so2": 23.84, "pm2_5": 71.44, "pm10": 87.23, "nh3": 14.06}, "dt": 1716562800}, {"main": {"aqi": 4}, "components": {"co": 700.95, "no": 0, "no2": 15.59, "o3": 105.86, "so2": 23.37, "pm2_5": 72.26, "pm10": 88.98, "nh3": 15.58}, "dt": 1716566400}, {"main": {"aqi": 4}, "components": {"co": 720.98, "no": 0, "no2": 15.77, "o3": 100.14, "so2": 23.13, "pm2_5": 72.89, "pm10": 89.74, "nh3": 16.09}, "dt": 1716570000}, {"main": {"aqi": 4}, "components": {"co": 700.95, "no": 0, "no2": 15.08, "o3": 98.71, "so2": 21.7, "pm2_5": 70.44, "pm10": 86.17, "nh3": 15.71}, "dt": 1716573600}, {"main": {"aqi": 4}, "components": {"co": 660.9, "no": 0, "no2": 13.71, "o3": 95.84, "so2": 19.55, "pm2_5": 66.2, "pm10": 79.92, "nh3": 14.95}, "dt": 1716577200}]}